<rt-scene>

<camera>
	<lookat vector3="0.0 0.0 1.0" />
	<eye	vector3="0.0 0.0 0.0" />
	<up		vector3="0.0 1.0 0.0" />
	<fov	angle="60 deg"/>
	<near double="1e-4" />
	<far  double="1e4" />
</camera>

<image>
	<width double="1024" />
	<height double="768" />
	<bgcolor color="0.0 0.0 0.0" />
	<samples-per-pixel int="20" />
</image>

<materials>
	<simplemat id="left">
		<diffuse color="0.75 0.25 0.25" />
		<specular color="0.0 0.0 0.0" />	
		<reflect color="1.0 1.0 1.0" />
		<transmit color="0.0 0.0 0.0" />
		<eta double="0.0"/>
		<n double="0"/>
		<isreflect bool="false"/>
		<istransmit bool="false"/>
	</simplemat>
	<simplemat id="right">
		<diffuse color="0.25 0.25 0.75" />
		<specular color="0.0 0.0 0.0" />	
		<reflect color="1.0 1.0 1.0" />
		<transmit color="0.0 0.0 0.0" />
		<eta double="0.0"/>
		<n double="0"/>
		<isreflect bool="false"/>
		<istransmit bool="false"/>
	</simplemat>
	<simplemat id="back">
		<diffuse color="0.75 0.75 0.75" />
		<specular color="0.0 0.0 0.0" />	
		<reflect color="1.0 1.0 1.0" />
		<transmit color="0.0 0.0 0.0" />
		<eta double="0.0"/>
		<n double="0"/>
		<isreflect bool="false"/>
		<istransmit bool="false"/>
	</simplemat>
	<simplemat id="front">
		<diffuse color="0.0 0.0 0.0" />
		<specular color="0.0 0.0 0.0" />	
		<reflect color="1.0 1.0 1.0" />
		<transmit color="0.0 0.0 0.0" />
		<eta double="0.0"/>
		<n double="0"/>
		<isreflect bool="false"/>
		<istransmit bool="false"/>
	</simplemat>
	<simplemat id="bottom">
		<diffuse color="0.75 0.75 0.75" />
		<specular color="0.0 0.0 0.0" />	
		<reflect color="1.0 1.0 1.0" />
		<transmit color="0.0 0.0 0.0" />
		<eta double="0.0"/>
		<n double="0"/>
		<isreflect bool="false"/>
		<istransmit bool="false"/>
	</simplemat>
	<simplemat id="top">
		<diffuse color="0.75 0.75 0.75" />
		<specular color="0.0 0.0 0.0" />	
		<reflect color="1.0 1.0 1.0" />
		<transmit color="0.0 0.0 0.0" />
		<eta double="0.0"/>
		<n double="0"/>
		<isreflect bool="false"/>
		<istransmit bool="false"/>
	</simplemat>
	<simplemat id="mirror">
		<diffuse color="0.1 0.1 0.1" />
		<specular color="0.0 0.0 0.0" />
		<reflect color="1.0 1.0 1.0" />
		<transmit color="0.0 0.0 0.0" />
		<eta double="0.0"/>
		<n double="0" />
		<isreflect bool="true"/>
		<istransmit bool="false"/>
	</simplemat>	
	<simplemat id="glass">
		<diffuse color="0.0 0.0 0.0" />
		<specular color="0.0 0.0 0.0" />
		<reflect color="0.0 0.0 0.0" />
		<transmit color="1.0 1.0 1.0" />
		<eta double="1.5"/>
		<n double="0" />
		<isreflect bool="false"/>
		<istransmit bool="true"/>
	</simplemat>	
</materials>

<objects>
	<sphere material="left">
		<center vector3="100004.0 -250.0 0.0" />
		<radius double="100000.0" />
	</sphere>
	<sphere material="right">
		<center vector3="-100004.0 -250 0.0" />
		<radius double="100000.0" />
	</sphere>
	<sphere material="back">
		<center vector3="0.0 0.0 100000.0" />
		<radius double="99980.0" />
	</sphere>
	<sphere material="top">
		<center vector3="0.0 150004.0 0.0" />
		<radius double="150000.0" />
	</sphere>
	<sphere material="bottom">
		<center vector3="0.0 -100004.0 0.0" />
		<radius double="100000.0" />
	</sphere>
	<sphere material="front">
		<center vector3="0.0 0.0 -100000.0" />
		<radius double="100000.0" />
	</sphere>	
	<sphere material="mirror">
		<center vector3="2.0 -2.5 17.0" />
		<radius double="1.5" />
	</sphere>
	<sphere material="glass">
		<center vector3="-2.0 -2.50 13.0" />
		<radius double="1.5" />
	</sphere>
</objects>

<lights>
	<arealight>
		<center vector3="0.0 3.99 15.0" />
		<radius double="2.0" />
		<normal vector3="0.0 1.0 0.0" />
		<num-samples int="1" />
		<color vector3="1.0 1.0 1.0" />
		<ka double="0.3" />
	</arealight>
</lights>

<integrator>
	<monte-carlo>
		<depth-of-recursion int="5" />
	</monte-carlo>
</integrator>


</rt-scene>